fingerprint_pro_server_api_sdk/__init__.py
fingerprint_pro_server_api_sdk/api_client.py
fingerprint_pro_server_api_sdk/base_model.py
fingerprint_pro_server_api_sdk/configuration.py
fingerprint_pro_server_api_sdk/dummy_pool.py
fingerprint_pro_server_api_sdk/extend_exception.py
fingerprint_pro_server_api_sdk/rest.py
fingerprint_pro_server_api_sdk/sealed.py
fingerprint_pro_server_api_sdk/webhook_validation.py
fingerprint_pro_server_api_sdk/api/__init__.py
fingerprint_pro_server_api_sdk/api/fingerprint_api.py
fingerprint_pro_server_api_sdk/models/__init__.py
fingerprint_pro_server_api_sdk/models/botd.py
fingerprint_pro_server_api_sdk/models/botd_bot.py
fingerprint_pro_server_api_sdk/models/botd_bot_result.py
fingerprint_pro_server_api_sdk/models/browser_details.py
fingerprint_pro_server_api_sdk/models/cloned_app.py
fingerprint_pro_server_api_sdk/models/deprecated_geolocation.py
fingerprint_pro_server_api_sdk/models/developer_tools.py
fingerprint_pro_server_api_sdk/models/emulator.py
fingerprint_pro_server_api_sdk/models/error.py
fingerprint_pro_server_api_sdk/models/error_code.py
fingerprint_pro_server_api_sdk/models/error_plain_response.py
fingerprint_pro_server_api_sdk/models/error_response.py
fingerprint_pro_server_api_sdk/models/events_get_response.py
fingerprint_pro_server_api_sdk/models/events_update_request.py
fingerprint_pro_server_api_sdk/models/factory_reset.py
fingerprint_pro_server_api_sdk/models/frida.py
fingerprint_pro_server_api_sdk/models/geolocation.py
fingerprint_pro_server_api_sdk/models/geolocation_city.py
fingerprint_pro_server_api_sdk/models/geolocation_continent.py
fingerprint_pro_server_api_sdk/models/geolocation_country.py
fingerprint_pro_server_api_sdk/models/geolocation_subdivision.py
fingerprint_pro_server_api_sdk/models/geolocation_subdivisions.py
fingerprint_pro_server_api_sdk/models/high_activity.py
fingerprint_pro_server_api_sdk/models/identification.py
fingerprint_pro_server_api_sdk/models/identification_confidence.py
fingerprint_pro_server_api_sdk-8.11.0.dist-info/licenses/LICENSE
fingerprint_pro_server_api_sdk-8.11.0.dist-info/METADATA
fingerprint_pro_server_api_sdk-8.11.0.dist-info/WHEEL
fingerprint_pro_server_api_sdk-8.11.0.dist-info/top_level.txt
fingerprint_pro_server_api_sdk-8.11.0.dist-info/RECORD
