Metadata-Version: 2.4
Name: fingerprint-pro-server-api-sdk
Version: 8.11.0
Summary: Fingerprint Server API allows you to search, update, and delete identification events in a server environment. It can be used for data exports, decision-making, and data analysis scenarios. Server API is intended for server-side usage, it's not intended to be used from the client side, whether it's a browser or a mobile device. 
Author: Fingerprint
Author-email: support@fingerprint.com
License: MIT
Project-URL: Changelog, https://github.com/fingerprintjs/fingerprint-pro-server-api-python-sdk/blob/main/CHANGELOG.md
Project-URL: Code, https://github.com/fingerprintjs/fingerprint-pro-server-api-python-sdk
Project-URL: Issue Tracker, https://github.com/fingerprintjs/fingerprint-pro-server-api-python-sdk/issues
Keywords: Swagger,Fingerprint Server API,browser,detection,fingerprint,identification,fingerprinting,browser-fingerprinting,browser-fingerprint,fraud-detection,fraud,audio-fingerprinting,fingerprintjs,fingerprintjs-pro,visitor-identifier
Classifier: Development Status :: 5 - Production/Stable
Classifier: Intended Audience :: Developers
Classifier: License :: OSI Approved :: MIT License
Classifier: Programming Language :: Python
Classifier: Programming Language :: Python :: 3.9
Classifier: Programming Language :: Python :: 3.10
Classifier: Programming Language :: Python :: 3.12
Classifier: Programming Language :: Python :: 3.12
Classifier: Programming Language :: Python :: Implementation :: PyPy
Classifier: Topic :: Software Development :: Libraries :: Python Modules
Classifier: Topic :: Security
License-File: LICENSE
Requires-Dist: certifi>=2023.7.22
Requires-Dist: python-dateutil>=2.5.3
Requires-Dist: urllib3>=1.23
Requires-Dist: cryptography
Requires-Dist: typing_extensions>=4.5
Dynamic: author
Dynamic: author-email
Dynamic: classifier
Dynamic: description
Dynamic: description-content-type
Dynamic: keywords
Dynamic: license
Dynamic: license-file
Dynamic: project-url
Dynamic: requires-dist
Dynamic: summary
